bootstrap_datepicker/__init__.py
bootstrap_datepicker/widgets.py
bootstrap_datepicker/static/css/bootstrap-datepicker3.standalone.min.css
bootstrap_datepicker/static/js/bootstrap-datepicker.js
bootstrap_datepicker/static/js/bootstrap-datepicker.min.js
bootstrap_datepicker/static/js/locales/bootstrap-datepicker-en-CA.min.js
bootstrap_datepicker/static/js/locales/bootstrap-datepicker.ar-DZ.min.js
bootstrap_datepicker/static/js/locales/bootstrap-datepicker.ar-tn.min.js
bootstrap_datepicker/static/js/locales/bootstrap-datepicker.ar.min.js
bootstrap_datepicker/static/js/locales/bootstrap-datepicker.az.min.js
bootstrap_datepicker/static/js/locales/bootstrap-datepicker.bg.min.js
bootstrap_datepicker/static/js/locales/bootstrap-datepicker.bm.min.js
bootstrap_datepicker/static/js/locales/bootstrap-datepicker.bn.min.js
bootstrap_datepicker/static/js/locales/bootstrap-datepicker.br.min.js
bootstrap_datepicker/static/js/locales/bootstrap-datepicker.bs.min.js
bootstrap_datepicker/static/js/locales/bootstrap-datepicker.ca.min.js
bootstrap_datepicker/static/js/locales/bootstrap-datepicker.cs.min.js
bootstrap_datepicker/static/js/locales/bootstrap-datepicker.cy.min.js
bootstrap_datepicker/static/js/locales/bootstrap-datepicker.da.min.js
bootstrap_datepicker/static/js/locales/bootstrap-datepicker.de.min.js
bootstrap_datepicker/static/js/locales/bootstrap-datepicker.el.min.js
bootstrap_datepicker/static/js/locales/bootstrap-datepicker.en-AU.min.js
bootstrap_datepicker/static/js/locales/bootstrap-datepicker.en-CA.min.js
bootstrap_datepicker/static/js/locales/bootstrap-datepicker.en-GB.min.js
bootstrap_datepicker/static/js/locales/bootstrap-datepicker.en-IE.min.js
bootstrap_datepicker/static/js/locales/bootstrap-datepicker.en-NZ.min.js
bootstrap_datepicker/static/js/locales/bootstrap-datepicker.en-US.min.js
bootstrap_datepicker/static/js/locales/bootstrap-datepicker.en-ZA.min.js
bootstrap_datepicker/static/js/locales/bootstrap-datepicker.eo.min.js
django_bootstrap_datepicker-1.5.0.dist-info/LICENSE
django_bootstrap_datepicker-1.5.0.dist-info/METADATA
django_bootstrap_datepicker-1.5.0.dist-info/WHEEL
django_bootstrap_datepicker-1.5.0.dist-info/top_level.txt
django_bootstrap_datepicker-1.5.0.dist-info/RECORD
