Metadata-Version: 2.1
Name: django-bootstrap-datepicker
Version: 1.5.0
Summary: Bootstrap 3/4/5 compatible datepicker for Django projects.
Home-page: https://github.com/pbucher/django-bootstrap-datepicker
Author: Paul Bucher
Author-email: paul@sandyfeetsoftware.com
License: Apache License 2.0
Classifier: Intended Audience :: Developers
Classifier: License :: OSI Approved :: Apache Software License
Classifier: Programming Language :: Python
Classifier: Programming Language :: Python :: 3
Classifier: Operating System :: OS Independent
Classifier: Topic :: Software Development :: Libraries
Classifier: Topic :: Utilities
Classifier: Environment :: Web Environment
Classifier: Framework :: Django
License-File: LICENSE
